README.md
setup.py
TMPPA/TMPPA.py
TMPPA.egg-info/PKG-INFO
TMPPA.egg-info/SOURCES.txt
TMPPA.egg-info/dependency_links.txt
TMPPA.egg-info/top_level.txt