Metadata-Version: 2.1
Name: TMPPA
Version: 0.1
Summary: Transfomación para Evaluación de modelos predictivos de la progresión acelerada de la Enfermedad Renal Crónica
Home-page: UNKNOWN
Author: Juan Carlos Guevara - Luis Hermogenes
Author-email: 
License: MIT
Platform: UNKNOWN
